graphene_django_auth/__init__.py
graphene_django_auth/graphene_django_auth.py
graphene_django_auth/models.py
graphene_django_auth/schema.py
graphene_django_auth-0.1.0.dist-info/DESCRIPTION.rst
graphene_django_auth-0.1.0.dist-info/METADATA
graphene_django_auth-0.1.0.dist-info/RECORD
graphene_django_auth-0.1.0.dist-info/WHEEL
graphene_django_auth-0.1.0.dist-info/metadata.json
graphene_django_auth-0.1.0.dist-info/top_level.txt
