Metadata-Version: 2.0
Name: graphene-django-auth
Version: 0.1.0
Summary: Implementation of a graphql schema for jwt authentication.
Home-page: https://github.com/kverdecia/graphene_django_auth
Author: Karel Antonio Verdecia Ortiz
Author-email: kverdecia@gmail.com
License: MIT license
Keywords: graphene_django_auth
Platform: UNKNOWN
Classifier: Development Status :: 2 - Pre-Alpha
Classifier: Intended Audience :: Developers
Classifier: License :: OSI Approved :: MIT License
Classifier: Natural Language :: English
Classifier: Programming Language :: Python :: 2
Classifier: Programming Language :: Python :: 2.6
Classifier: Programming Language :: Python :: 2.7
Classifier: Programming Language :: Python :: 3
Classifier: Programming Language :: Python :: 3.3
Classifier: Programming Language :: Python :: 3.4
Classifier: Programming Language :: Python :: 3.5
Requires-Dist: graphene
Requires-Dist: graphene-django
Requires-Dist: pyjwt
